libopentims_cpp.cp39-win32.pyd
opentimspy_cpp.cp39-win32.pyd
opentimspy/__init__.py
opentimspy/dimension_translations.py
opentimspy/misc.py
opentimspy/opentims.py
opentimspy/plotting.py
opentimspy/sql.py
opentimspy/opentims++/bruker_api.h
opentimspy/opentims++/converters.h
opentimspy/opentims++/mio.hpp
opentimspy/opentims++/opentims.h
opentimspy/opentims++/opentims_all.h
opentimspy/opentims++/platform.h
opentimspy/opentims++/platform_os.h
opentimspy/opentims++/scan2inv_ion_mobility_converter.h
opentimspy/opentims++/so_manager.h
opentimspy/opentims++/thread_mgr.h
opentimspy/opentims++/tof2mz_converter.h
opentimspy/opentims++/sqlite/sqlite3.h
opentimspy/opentims++/zstd/zstd.h
opentimspy-1.0.16.data/scripts/opentims_display_frame.py
opentimspy-1.0.16.data/scripts/opentims_extract_tdf.py
opentimspy-1.0.16.data/scripts/opentims_frame_sum.py
opentimspy-1.0.16.data/scripts/opentims_summary.py
opentimspy-1.0.16.data/scripts/opentims_verify.py
opentimspy-1.0.16.dist-info/LICENCE
opentimspy-1.0.16.dist-info/METADATA
opentimspy-1.0.16.dist-info/WHEEL
opentimspy-1.0.16.dist-info/top_level.txt
opentimspy-1.0.16.dist-info/RECORD
